ziyy/__init__.py
ziyy/__main__.py
ziyy-1.0.0.dist-info/METADATA
ziyy-1.0.0.dist-info/WHEEL
ziyy-1.0.0.dist-info/top_level.txt
ziyy-1.0.0.dist-info/RECORD
