Metadata-Version: 2.1
Name: ziyy
Version: 1.0.0
Summary: Convenient Terminal Output Styler.
Author-email: alMukaafih <almukaafih@gmail.com>
Project-URL: Homepage, https://github.com/alMukaafih/ziyy
Project-URL: Documentation, https://github.com/alMukaafih/ziyy#readme
Project-URL: Repository, https://github.com/alMukaafih/ziyy.git
Project-URL: Issues, https://github.com/alMukaafih/ziyy/issues
Classifier: Programming Language :: Python :: 3
Classifier: License :: OSI Approved :: MIT License
Classifier: Operating System :: OS Independent
Requires-Python: >=3.8
